helloworld.py
alphascope-0.0.1.dist-info/LICENSE
alphascope-0.0.1.dist-info/METADATA
alphascope-0.0.1.dist-info/WHEEL
alphascope-0.0.1.dist-info/top_level.txt
alphascope-0.0.1.dist-info/RECORD
